clime_productivity/__init__.py
clime_productivity/args.py
clime_productivity/graph.py
clime_productivity/main.py
clime_productivity/version.py
clime_productivity-0.4.2.dist-info/LICENSE
clime_productivity-0.4.2.dist-info/METADATA
clime_productivity-0.4.2.dist-info/WHEEL
clime_productivity-0.4.2.dist-info/entry_points.txt
clime_productivity-0.4.2.dist-info/top_level.txt
clime_productivity-0.4.2.dist-info/RECORD
