Metadata-Version: 2.1
Name: clime-productivity
Version: 0.4.2
Summary: CLIME - Productivity
Home-page: https://ssl.cs.luc.edu/projects/metricsDashboard
Author: Software and Systems Laboratory - Loyola University Chicago
Author-email: ssl-metrics@ssl.luc.edu
License: BSD
Project-URL: Bug Tracker, https://github.com/SoftwareSystemsLaboratory/clime-productivity/issues
Project-URL: GitHub Repository, https://github.com/SoftwareSystemsLaboratory/clime-productivity
Keywords: bugzilla,bus factor,bus factor,cloc,commits,commits,delta lines of code,engineering,git,git,github,github,gitlab,installable,issue density,issue density,issue spoilage,issues,issues,kloc,lines of code,longitudinal graphs,loyola university chicago,loyola,luc,metrics,metrics,mining,productivity,python,repository mining,repository,simple,sloccount,software engineering,software metrics,software systems laboratory,software,ssl,thousands of lines of code,tool,vcs
Platform: UNKNOWN
Classifier: Development Status :: 4 - Beta
Classifier: Intended Audience :: Science/Research
Classifier: Intended Audience :: Developers
Classifier: License :: OSI Approved :: BSD License
Classifier: Programming Language :: Python
Classifier: Programming Language :: Python :: 3
Classifier: Programming Language :: Python :: 3.9
Classifier: Programming Language :: Python :: 3 :: Only
Classifier: Topic :: Software Development
Classifier: Topic :: Scientific/Engineering
Classifier: Operating System :: POSIX
Classifier: Operating System :: Unix
Classifier: Operating System :: MacOS
Requires-Python: >=3.9
License-File: LICENSE
Requires-Dist: numpy
Requires-Dist: matplotlib
Requires-Dist: pandas
